{
  "Buxoro davlat pedagogika instituti": {
    "website": "https://buxdpi.uz",
    "master_directions": [],
    "doctorate_directions": [
      {
        "dirid": "",
        "name": "Buxoro davlat pedagogika institutida mustaqil izlanuvchilikka (DSc, Phd) quyidagi ixtisosliklar mavjud:",
        "exam_subjects": [],
        "study_forms": [],
        "languages": []
      },
      {
        "dirid": "",
        "name": "Buxoro davlat pedagogika institutida oliy ta'limdan keyingi ta'lim doktorantura, tayanch doktorantura (DSc, Phd) quyidagi ixtisosliklar mavjud:",
        "exam_subjects": [],
        "study_forms": [],
        "languages": []
      }
    ],
    "master_count": 0,
    "doctorate_count": 2,
    "note": "website:https://buxdpi.uz pages=5"
  },
  "Buxoro davlat texnika universiteti": {
    "website": "https://bstu.uz/",
    "master_directions": [],
    "doctorate_directions": [
      {
        "dirid": "",
        "name": "02.00.08 – «Neft va gaz kimyosi va texnologiyasi» ixtisosligi bo'yicha tayanch doktorantura va doktoranturaga kirish imtihoni dasturi",
        "exam_subjects": [],
        "study_forms": [],
        "languages": []
      },
      {
        "dirid": "",
        "name": "02.00.11– «Kolloid va membrana kimyosi» ixtisosligi bo'yicha tayanch doktoranturaga (PhD) kirish imtihoni dasturi",
        "exam_subjects": [],
        "study_forms": [],
        "languages": []
      },
      {
        "dirid": "",
        "name": "02.00.13 – «Noorganik moddalar va ular asosidagi materiallar texnologiyasi» ixtisosligi bo'yicha doktoranturaga (PhD) kirish imtihoni dasturi",
        "exam_subjects": [],
        "study_forms": [],
        "languages": []
      },
      {
        "dirid": "",
        "name": "02.00.14– «Organik moddalar va ular asosidagi materiallar texnologiyasi » ixtisosligi bo'yicha tayanch doktoranturaga (PhD) kirish imtihoni dasturi",
        "exam_subjects": [],
        "study_forms": [],
        "languages": []
      },
      {
        "dirid": "",
        "name": "05.06.03 – «Teri, mo‘yna, poyabzal va teri-galantereya buyumlari texnologiyasi» ixtisosligi bo‘yicha tayanch doktoranturaga (PhD) kirish imtihoni dasturi",
        "exam_subjects": [],
        "study_forms": [],
        "languages": []
      },
      {
        "dirid": "",
        "name": "05.06.04 – «Tikuvchilik buyumlari texnologiyasi va kostyum dizayni» ixtisosligi bo‘yicha tayanch doktoranturaga (PhD) kirish imtihoni dasturi",
        "exam_subjects": [],
        "study_forms": [],
        "languages": []
      },
      {
        "dirid": "",
        "name": "05.09.07 – «Gidravlika va muhandislik gidrologiyasi» ixtisosligi bo‘yicha tayanch doktoranturaga (PhD) kirish imtihoni dasturi",
        "exam_subjects": [],
        "study_forms": [],
        "languages": []
      },
      {
        "dirid": "",
        "name": "08.00.10 – «Demografiya. Mehnat iqtisodiyoti» ixtisosligi bo‘yicha doktoranturaga (PhD) kirish imtihoni dasturi",
        "exam_subjects": [],
        "study_forms": [],
        "languages": []
      },
      {
        "dirid": "",
        "name": "08.00.12 – «Mintaqaviy iqtisodiyot» ixtisosligi bo‘yicha doktoranturaga (PhD) kirish imtihoni dasturi",
        "exam_subjects": [],
        "study_forms": [],
        "languages": []
      }
    ],
    "master_count": 0,
    "doctorate_count": 9,
    "note": "website:https://bstu.uz/ pages=9"
  },
  "Chirchiq davlat pedagogika universiteti": {
    "website": "https://www.cspi.uz",
    "master_directions": [],
    "doctorate_directions": [
      {
        "dirid": "",
        "name": "Biologiya fanlari (PhD)",
        "exam_subjects": [],
        "study_forms": [],
        "languages": []
      },
      {
        "dirid": "",
        "name": "Chirchiq davlat pedagogika universiteti huzuridagi pedagogika fanlari boʻyicha ilmiy darajalarni beruvchi ilmiy kengash 2019-yildan buyon faoliyat olib bormoqda",
        "exam_subjects": [],
        "study_forms": [],
        "languages": []
      },
      {
        "dirid": "",
        "name": "Ilmiy Kengashlar Pedagogika fanlari (PhD)",
        "exam_subjects": [],
        "study_forms": [],
        "languages": []
      },
      {
        "dirid": "",
        "name": "Kimyo fanlari (PhD)",
        "exam_subjects": [],
        "study_forms": [],
        "languages": []
      },
      {
        "dirid": "",
        "name": "Pedagogika fanlari (DSc & PhD)",
        "exam_subjects": [],
        "study_forms": [],
        "languages": []
      },
      {
        "dirid": "",
        "name": "Pedagogika fanlari bo‘yicha fan doktori (DSc) va falsafa doktori (PhD) ilmiy darajalarini beruvchi ilmiy kengash",
        "exam_subjects": [],
        "study_forms": [],
        "languages": []
      }
    ],
    "master_count": 0,
    "doctorate_count": 6,
    "note": "website:https://www.cspi.uz pages=16"
  },
  "Denov tadbirkorlik va pedagogika instituti": {
    "website": "https://dtpi.uz",
    "master_directions": [
      {
        "dirid": "70220300",
        "name": "Tarix(mamlakatlar va yo’nalishlar bo’yicha)",
        "exam_subjects": [],
        "study_forms": [],
        "languages": []
      }
    ],
    "doctorate_directions": [
      {
        "dirid": "",
        "name": "Doktorantura – Denov tadbirkorlik va pedagogika instituti INSTITUT Institut haqida",
        "exam_subjects": [],
        "study_forms": [],
        "languages": []
      },
      {
        "dirid": "",
        "name": "Magistrlik dissertatsiyasi himoyasi – Denov tadbirkorlik va pedagogika instituti INSTITUT Institut haqida",
        "exam_subjects": [],
        "study_forms": [],
        "languages": []
      },
      {
        "dirid": "",
        "name": "Magistrlik dissertatsiyasi mavzulari – Denov tadbirkorlik va pedagogika instituti INSTITUT Institut haqida",
        "exam_subjects": [],
        "study_forms": [],
        "languages": []
      },
      {
        "dirid": "",
        "name": "PHD MUVAFFAQIYATLI HIMOYA QILINDI – Denov tadbirkorlik va pedagogika instituti INSTITUT Institut haqida",
        "exam_subjects": [],
        "study_forms": [],
        "languages": []
      }
    ],
    "master_count": 1,
    "doctorate_count": 4,
    "note": "website:https://dtpi.uz pages=16"
  },
  "Nukus davlat pedagogika instituti": {
    "website": "https://ndpi.uz",
    "master_directions": [],
    "doctorate_directions": [
      {
        "dirid": "",
        "name": "> Doktorantura (DSc) mutaxassisliklari va mustaqil izlanuvchilikka qabul imtihoni bo‘lib o‘tdi – AJINIYOZ NOMIDAGI NUKUS DAVLAT PEDAGOGIKA INSTITUTI",
        "exam_subjects": [],
        "study_forms": [],
        "languages": []
      }
    ],
    "master_count": 0,
    "doctorate_count": 1,
    "note": "website:https://ndpi.uz pages=24"
  },
  "O'zbekiston davlat jahon tillari universiteti": {
    "website": "https://uzswlu.uz",
    "master_directions": [],
    "doctorate_directions": [
      {
        "dirid": "",
        "name": "Filologiya fanlari bo ‘ yicha falsafa doktori ( PhD ) dissertatsiyasi himoyasi",
        "exam_subjects": [],
        "study_forms": [],
        "languages": []
      },
      {
        "dirid": "",
        "name": "Filologiya fanlari bo‘yicha falsafa doktori (PhD) dissertatsiyasi himoyasi Ilmiy kengash majlisi",
        "exam_subjects": [],
        "study_forms": [],
        "languages": []
      },
      {
        "dirid": "",
        "name": "Filologiya fanlari bo‘yicha falsafa doktori (PhD) dissertatsiyasi himoyasi Ilmiy kengash majlisi Oʻzbekiston davlat jahon tillari universiteti Login (Xodim)",
        "exam_subjects": [],
        "study_forms": [],
        "languages": []
      }
    ],
    "master_count": 0,
    "doctorate_count": 3,
    "note": "website:https://uzswlu.uz pages=9"
  },
  "Oriental universiteti": {
    "website": "https://orientaluniversity.uz",
    "master_directions": [
      {
        "dirid": "70410901",
        "name": "Biznesni boshqarish (MBA)",
        "exam_subjects": [],
        "study_forms": [],
        "languages": []
      },
      {
        "dirid": "70610401",
        "name": "Dasturiy injiniring",
        "exam_subjects": [],
        "study_forms": [],
        "languages": []
      },
      {
        "dirid": "70230101",
        "name": "Filologiya",
        "exam_subjects": [],
        "study_forms": [],
        "languages": []
      },
      {
        "dirid": "70310101",
        "name": "Iqtisodiyot",
        "exam_subjects": [],
        "study_forms": [],
        "languages": []
      },
      {
        "dirid": "70411101",
        "name": "Jahon iqtisodiyoti",
        "exam_subjects": [],
        "study_forms": [],
        "languages": []
      },
      {
        "dirid": "70610301",
        "name": "Kompyuter injiniringi",
        "exam_subjects": [],
        "study_forms": [],
        "languages": []
      },
      {
        "dirid": "70230201",
        "name": "Lingvistika",
        "exam_subjects": [],
        "study_forms": [],
        "languages": []
      },
      {
        "dirid": "70411201",
        "name": "Marketing",
        "exam_subjects": [],
        "study_forms": [],
        "languages": []
      },
      {
        "dirid": "70540101",
        "name": "Matematika",
        "exam_subjects": [],
        "study_forms": [],
        "languages": []
      },
      {
        "dirid": "70610304",
        "name": "Ma’lumotlar ilmi (Data Science)",
        "exam_subjects": [],
        "study_forms": [],
        "languages": []
      },
      {
        "dirid": "70410801",
        "name": "Menejment",
        "exam_subjects": [],
        "study_forms": [],
        "languages": []
      },
      {
        "dirid": "70110101",
        "name": "Pedagogika",
        "exam_subjects": [],
        "study_forms": [],
        "languages": []
      },
      {
        "dirid": "70313001",
        "name": "Psixologiya",
        "exam_subjects": [],
        "study_forms": [],
        "languages": []
      },
      {
        "dirid": "70310901",
        "name": "Raqamli iqtisodiyot",
        "exam_subjects": [],
        "study_forms": [],
        "languages": []
      },
      {
        "dirid": "70610501",
        "name": "Sun’iy intellekt",
        "exam_subjects": [],
        "study_forms": [],
        "languages": []
      },
      {
        "dirid": "70110201",
        "name": "Ta’lim va tarbiya",
        "exam_subjects": [],
        "study_forms": [],
        "languages": []
      }
    ],
    "doctorate_directions": [],
    "master_count": 16,
    "doctorate_count": 0,
    "note": "website:https://orientaluniversity.uz pages=9"
  },
  "Qarshi davlat universiteti": {
    "website": "https://qarshidu.uz/oz",
    "master_directions": [],
    "doctorate_directions": [
      {
        "dirid": "",
        "name": "“01.01.01 Matematik analiz” ixtisosligi bo‘yicha tayanch doktoranturaga kiruvchi talabgorlarning yakuniy qaydnomasi",
        "exam_subjects": [],
        "study_forms": [],
        "languages": []
      },
      {
        "dirid": "",
        "name": "“02.00.03 Organik kimyo” ixtisosligi bo‘yicha tayanch doktoranturaga kiruvchi talabgorlarning yakuniy qaydnomasi",
        "exam_subjects": [],
        "study_forms": [],
        "languages": []
      },
      {
        "dirid": "",
        "name": "“02.00.10 Biorganik kimyo” ixtisosligi bo‘yicha tayanch doktoranturaga kiruvchi talabgorlarning yakuniy qaydnomasi",
        "exam_subjects": [],
        "study_forms": [],
        "languages": []
      },
      {
        "dirid": "",
        "name": "“02.00.14 Organik moddalar va ular asosidagi materiallar texnologiyasi” ixtisosligi bo‘yicha tayanch doktoranturaga kiruvchi talabgorning yakuniy qaydnomasi",
        "exam_subjects": [],
        "study_forms": [],
        "languages": []
      },
      {
        "dirid": "",
        "name": "“05.01.07-Matematik modellashtirish. Sonli usullar va dasturlar majmui” ixtisosligi bo‘yicha tayanch doktoranturaga kiruvchi talabgorlarning yakuniy qaydnomasi",
        "exam_subjects": [],
        "study_forms": [],
        "languages": []
      },
      {
        "dirid": "",
        "name": "“08.00.12-Mintaqaviy iqtisodiyot” ixtisosligi bo‘yicha tayanch doktoranturaga kiruvchi talabgorlarning yakuniy qaydnomasi",
        "exam_subjects": [],
        "study_forms": [],
        "languages": []
      },
      {
        "dirid": "",
        "name": "“11.00.02–Iqtisodiy va ijtimoiy geografiya” ixtisosligi bo‘yicha tayanch doktoranturaga kiruvchi talabgorlarning yakuniy qaydnomasi",
        "exam_subjects": [],
        "study_forms": [],
        "languages": []
      },
      {
        "dirid": "",
        "name": "“13.00.01-Pedagogika nazariyasi. Pedagogik ta’limotlar tarixi” ixtisosligi bo‘yicha tayanch doktoranturaga kiruvchi talabgorlarning yakuniy qaydnomasi",
        "exam_subjects": [],
        "study_forms": [],
        "languages": []
      },
      {
        "dirid": "",
        "name": "“19.00.06-Yosh va pedagogik psixologiya. Rivojlanish psixologiyasi” ixtisosligi bo‘yicha tayanch doktoranturaga kiruvchi talabgorlarning yakuniy qaydnomasi",
        "exam_subjects": [],
        "study_forms": [],
        "languages": []
      },
      {
        "dirid": "",
        "name": "“19.00.06-Yosh va pedagogik psixologiya.Rivojlanish psixologiyasi” ixtisosligi bo’yicha tayanch doktoranturaga kiruvchi talabgorlarning yakuniy qaydnomasi",
        "exam_subjects": [],
        "study_forms": [],
        "languages": []
      }
    ],
    "master_count": 0,
    "doctorate_count": 10,
    "note": "website:https://qarshidu.uz/oz pages=29"
  },
  "Samarqand davlat arxitektura-qurilish universiteti": {
    "website": "https://samgasi.uz/",
    "master_directions": [
      {
        "dirid": "70730101",
        "name": "Bino va inshootlar arxitekturasi",
        "exam_subjects": [],
        "study_forms": [],
        "languages": []
      },
      {
        "dirid": "70730307",
        "name": "Bino va inshootlarni konstruktiv loyihalash",
        "exam_subjects": [],
        "study_forms": [],
        "languages": []
      },
      {
        "dirid": "70411302",
        "name": "Biznesni boshqarish (Master of Business Administration — MBA)",
        "exam_subjects": [],
        "study_forms": [],
        "languages": []
      },
      {
        "dirid": "70210401",
        "name": "Dizayn (turlari boʼyicha)",
        "exam_subjects": [],
        "study_forms": [],
        "languages": []
      },
      {
        "dirid": "70722502",
        "name": "Geodeziya va kartografiya (funktsiyalari boʼyicha)",
        "exam_subjects": [],
        "study_forms": [],
        "languages": []
      },
      {
        "dirid": "70723301",
        "name": "Geomatika muhandisligi",
        "exam_subjects": [],
        "study_forms": [],
        "languages": []
      },
      {
        "dirid": "70310102",
        "name": "Iqtisodiyot (tarmoqlar va sohalar boʼyicha)",
        "exam_subjects": [],
        "study_forms": [],
        "languages": []
      },
      {
        "dirid": "70722801",
        "name": "Kadastr (faoliyat turlari boʼyicha)",
        "exam_subjects": [],
        "study_forms": [],
        "languages": []
      },
      {
        "dirid": "70731001",
        "name": "Koʼchmas mulkni baholash va boshqarish",
        "exam_subjects": [],
        "study_forms": [],
        "languages": []
      },
      {
        "dirid": "70212201",
        "name": "Madaniy meros obʼektlarini saqlash va himoyalash",
        "exam_subjects": [],
        "study_forms": [],
        "languages": []
      },
      {
        "dirid": "70730401",
        "name": "Muhandislik kommunikatsiya tizimlari, qurilishi va montaji (turlari boʼyicha)",
        "exam_subjects": [],
        "study_forms": [],
        "languages": []
      },
      {
        "dirid": "70710404",
        "name": "Oqova suvlarni tozalash va suv resurslarini muhofaza qilish",
        "exam_subjects": [],
        "study_forms": [],
        "languages": []
      },
      {
        "dirid": "70730701",
        "name": "Qurilish materiallari, buyumlari, konstruktsiyalari va ularni ishlab chiqarish texnologiyalari",
        "exam_subjects": [],
        "study_forms": [],
        "languages": []
      },
      {
        "dirid": "70730308",
        "name": "Seismic resistance of buildings and structures",
        "exam_subjects": [],
        "study_forms": [],
        "languages": []
      },
      {
        "dirid": "70730202",
        "name": "Shahar transporti xoʼjaligi va aloqa yoʼllari",
        "exam_subjects": [],
        "study_forms": [],
        "languages": []
      },
      {
        "dirid": "70730103",
        "name": "Shaharsozlik va landshaft arxitekturasi",
        "exam_subjects": [],
        "study_forms": [],
        "languages": []
      },
      {
        "dirid": "70722701",
        "name": "Yerni masofadan zondlash va GAT-texnologiyalari",
        "exam_subjects": [],
        "study_forms": [],
        "languages": []
      },
      {
        "dirid": "70730102",
        "name": "Аrxitektura nazariyasi va tarixi, arxitektura yodgorliklarini tiklash",
        "exam_subjects": [],
        "study_forms": [],
        "languages": []
      }
    ],
    "doctorate_directions": [],
    "master_count": 18,
    "doctorate_count": 0,
    "note": "website:https://samgasi.uz/ pages=11"
  },
  "Termiz davlat muhandislik va agrotexnologiyalar universiteti": {
    "website": "https://tdmau.uz",
    "master_directions": [
      {
        "dirid": "70810202",
        "name": "Agrokimyo",
        "exam_subjects": [],
        "study_forms": [],
        "languages": []
      },
      {
        "dirid": "70810401",
        "name": "Agronomiya",
        "exam_subjects": [],
        "study_forms": [],
        "languages": []
      },
      {
        "dirid": "70520201",
        "name": "Atrof-muhit muhandisligi",
        "exam_subjects": [],
        "study_forms": [],
        "languages": []
      },
      {
        "dirid": "70710401",
        "name": "Atrof-muhit muhofazasi (tarmoqlar va sohalar bo’yicha)",
        "exam_subjects": [],
        "study_forms": [],
        "languages": []
      },
      {
        "dirid": "70811101",
        "name": "Dorivor o‘simliklarni yetishtirish va qayta ishlash texnologiyasi",
        "exam_subjects": [],
        "study_forms": [],
        "languages": []
      },
      {
        "dirid": "70710601",
        "name": "Elektr ta’minoti (tarmoqlar bo‘yicha)",
        "exam_subjects": [],
        "study_forms": [],
        "languages": []
      },
      {
        "dirid": "70720801",
        "name": "Foydali qazilma konlarini qazish",
        "exam_subjects": [],
        "study_forms": [],
        "languages": []
      },
      {
        "dirid": "70410102",
        "name": "Iqtisodiyot",
        "exam_subjects": [],
        "study_forms": [],
        "languages": []
      },
      {
        "dirid": "70710101",
        "name": "Kimyoviy texnologiya (ishlab chiqarish turlari bo‘yicha)",
        "exam_subjects": [],
        "study_forms": [],
        "languages": []
      },
      {
        "dirid": "70820101",
        "name": "O‘rmonchilik mutaxassisligi bo‘yicha",
        "exam_subjects": [],
        "study_forms": [],
        "languages": []
      },
      {
        "dirid": "70810501",
        "name": "O‘simliklar himoyasi va karantini",
        "exam_subjects": [],
        "study_forms": [],
        "languages": []
      },
      {
        "dirid": "70720705",
        "name": "Paxtani dastlabki ishlash va urug‘tayyorlash texnologiyasi",
        "exam_subjects": [],
        "study_forms": [],
        "languages": []
      },
      {
        "dirid": "70730301",
        "name": "Qurilish muhandisligi",
        "exam_subjects": [],
        "study_forms": [],
        "languages": []
      },
      {
        "dirid": "70811003",
        "name": "Sabzavotchilik, polizchilik va kartoshkachilik",
        "exam_subjects": [],
        "study_forms": [],
        "languages": []
      },
      {
        "dirid": "70810601",
        "name": "Seleksiya va urug‘chilik",
        "exam_subjects": [],
        "study_forms": [],
        "languages": []
      },
      {
        "dirid": "70710901",
        "name": "Texnologik jarayonlar va ishlab chiqarishni avtomatlashtirish",
        "exam_subjects": [],
        "study_forms": [],
        "languages": []
      },
      {
        "dirid": "70720701",
        "name": "To‘qimachilik mahsulotlari texnologiyasi",
        "exam_subjects": [],
        "study_forms": [],
        "languages": []
      },
      {
        "dirid": "70711401",
        "name": "Transport vositalari muhandisligi",
        "exam_subjects": [],
        "study_forms": [],
        "languages": []
      },
      {
        "dirid": "70810203",
        "name": "Tuproqshunoslik",
        "exam_subjects": [],
        "study_forms": [],
        "languages": []
      },
      {
        "dirid": "70840104",
        "name": "Veterinariya akusherligi va hayvonlarni ko’paytirish biotexnikasi",
        "exam_subjects": [],
        "study_forms": [],
        "languages": []
      },
      {
        "dirid": "70721403",
        "name": "Yengil sanoat mahsulotlari texnologiyasi va jihozlari (mahsulotturlari bo’yicha)",
        "exam_subjects": [],
        "study_forms": [],
        "languages": []
      },
      {
        "dirid": "70712501",
        "name": "Yer usti transport vositalari va tizimlari (transport turlari bo’yicha)",
        "exam_subjects": [],
        "study_forms": [],
        "languages": []
      }
    ],
    "doctorate_directions": [],
    "master_count": 22,
    "doctorate_count": 0,
    "note": "website:https://tdmau.uz pages=18"
  },
  "TIQXMMI milliy tadqiqot universiteti": {
    "website": "https://tiiame.uz/",
    "master_directions": [
      {
        "dirid": "70810401",
        "name": "Aniq koordinatali qishloq xo‘jaligi",
        "exam_subjects": [],
        "study_forms": [],
        "languages": []
      },
      {
        "dirid": "70710401",
        "name": "Atrof-muhit muhofazasi (tarmoqlar va sohalar bo'yicha)",
        "exam_subjects": [],
        "study_forms": [],
        "languages": []
      },
      {
        "dirid": "70410101",
        "name": "Buxgalteriya hisobi (tarmoqlar va sohalar bo‘yicha)",
        "exam_subjects": [],
        "study_forms": [],
        "languages": []
      },
      {
        "dirid": "70710601",
        "name": "Elektr ta’minoti (suv xo‘jaligida)",
        "exam_subjects": [],
        "study_forms": [],
        "languages": []
      },
      {
        "dirid": "70710901",
        "name": "Energiya tejamkorligi va energoaudit (suv xo‘jaligida)",
        "exam_subjects": [],
        "study_forms": [],
        "languages": []
      },
      {
        "dirid": "70812801",
        "name": "GES qurilishi va ulardan foydalanish",
        "exam_subjects": [],
        "study_forms": [],
        "languages": []
      },
      {
        "dirid": "70722601",
        "name": "Geodeziya va geoinformatika",
        "exam_subjects": [],
        "study_forms": [],
        "languages": []
      },
      {
        "dirid": "70530804",
        "name": "Gidravlika va muhandislik gidrologiyasi",
        "exam_subjects": [],
        "study_forms": [],
        "languages": []
      },
      {
        "dirid": "70812401",
        "name": "Gidromelioratsiya ishlarini mexanizatsiyalashtirish",
        "exam_subjects": [],
        "study_forms": [],
        "languages": []
      },
      {
        "dirid": "70812305",
        "name": "Gidromelioratsiya tizimlaridan foydalanish",
        "exam_subjects": [],
        "study_forms": [],
        "languages": []
      },
      {
        "dirid": "70730901",
        "name": "Gidrotexnika inshootlari (suv xo‘jaligida)",
        "exam_subjects": [],
        "study_forms": [],
        "languages": []
      },
      {
        "dirid": "70730904",
        "name": "Gidrotexnika inshootlari qurilishini tashkil yetish va texnologiyasi",
        "exam_subjects": [],
        "study_forms": [],
        "languages": []
      },
      {
        "dirid": "70812501",
        "name": "Gidrotexnika inshootlaridan foydalanish, ularning ishonchliligi va xavfsizligi",
        "exam_subjects": [],
        "study_forms": [],
        "languages": []
      },
      {
        "dirid": "70810503",
        "name": "Intellektual datchiklar va texnologiyalar",
        "exam_subjects": [],
        "study_forms": [],
        "languages": []
      },
      {
        "dirid": "70412501",
        "name": "Marketing (suv xo‘jaligida)",
        "exam_subjects": [],
        "study_forms": [],
        "languages": []
      },
      {
        "dirid": "70812302",
        "name": "Melioratsiya va sug‘orma dehqonchilik",
        "exam_subjects": [],
        "study_forms": [],
        "languages": []
      },
      {
        "dirid": "70411201",
        "name": "Menejment (suv xo‘jaligida)",
        "exam_subjects": [],
        "study_forms": [],
        "languages": []
      },
      {
        "dirid": "70710505",
        "name": "Mini va mikro gidroelektrostansiyalar",
        "exam_subjects": [],
        "study_forms": [],
        "languages": []
      },
      {
        "dirid": "70111202",
        "name": "Muhandislik grafikasi va dizayn nazariyasi",
        "exam_subjects": [],
        "study_forms": [],
        "languages": []
      },
      {
        "dirid": "70711001",
        "name": "Muqobil energiya manbalari (turlari bo‘yicha)",
        "exam_subjects": [],
        "study_forms": [],
        "languages": []
      },
      {
        "dirid": "70812502",
        "name": "Nasos stansiyalari va qurilmalaridan foydalanish va tashxisi",
        "exam_subjects": [],
        "study_forms": [],
        "languages": []
      },
      {
        "dirid": "70810501",
        "name": "Qishloq va suv xo‘jaligida energiya ta’minoti",
        "exam_subjects": [],
        "study_forms": [],
        "languages": []
      },
      {
        "dirid": "70810101",
        "name": "Qishloq xo‘jaligini mexanizatsiyalashtirish (tarmoqlar bo‘yicha)",
        "exam_subjects": [],
        "study_forms": [],
        "languages": []
      },
      {
        "dirid": "70812307",
        "name": "Suv resurslaridan mukammal foydalanish va boshqarish",
        "exam_subjects": [],
        "study_forms": [],
        "languages": []
      },
      {
        "dirid": "70812306",
        "name": "Suv tejamkor sug‘orish texnologiyalari",
        "exam_subjects": [],
        "study_forms": [],
        "languages": []
      },
      {
        "dirid": "70810502",
        "name": "Suv xo‘jaligida Smart (intellektual) o‘lchash tizimlari va asboblari",
        "exam_subjects": [],
        "study_forms": [],
        "languages": []
      },
      {
        "dirid": "70412301",
        "name": "Suv xo‘jaligini tashkil etish va boshqarish",
        "exam_subjects": [],
        "study_forms": [],
        "languages": []
      },
      {
        "dirid": "70711401",
        "name": "Texnologik jarayonlar va ishlab chiqarishni avtomatlashtirish (suv xo‘jaligida)",
        "exam_subjects": [],
        "study_forms": [],
        "languages": []
      },
      {
        "dirid": "70810601",
        "name": "Yer resurslaridan foydalanish va boshqarish",
        "exam_subjects": [],
        "study_forms": [],
        "languages": []
      }
    ],
    "doctorate_directions": [],
    "master_count": 29,
    "doctorate_count": 0,
    "note": "website:https://tiiame.uz/ pages=27"
  },
  "Toshkent arxitektura-qurilish universiteti": {
    "website": "https://taqu.uz",
    "master_directions": [],
    "doctorate_directions": [
      {
        "dirid": "",
        "name": "Abdullaev Ibroxim Numanovichning texnika fanlari doktori (DSc) dissertatsiya ishi himoyasi to‘g‘risida",
        "exam_subjects": [],
        "study_forms": [],
        "languages": []
      },
      {
        "dirid": "",
        "name": "Aimbetov Islam Sapari‘mbet uli‘ning arxitektura fanlari falsafa doktori (PhD) dissertatsiya ishi himoyasi to‘g‘risida",
        "exam_subjects": [],
        "study_forms": [],
        "languages": []
      },
      {
        "dirid": "",
        "name": "Arifdjanova Zilola Dilshodovnaning iqtisodiyot fanlari bo‘yicha falsafa doktori (PhD) dissertatsiya ishi himoyasi to‘g‘risida",
        "exam_subjects": [],
        "study_forms": [],
        "languages": []
      },
      {
        "dirid": "",
        "name": "Karimov Inomjon Ortikbayevichning iqtisodiyot fanlari bo‘yicha falsafa doktori (PhD) dissertatsiya ishi himoyasi to‘g‘risida",
        "exam_subjects": [],
        "study_forms": [],
        "languages": []
      },
      {
        "dirid": "",
        "name": "Meliqulov G'ayrat Abdug'afforovichning arxitektura fanlari doktori (DSc) dissertatsiya ishi himoyasi to‘g‘risida",
        "exam_subjects": [],
        "study_forms": [],
        "languages": []
      },
      {
        "dirid": "",
        "name": "Mirpulatova Munis Akmal qizining arxitektura fanlari bo‘yicha falsafa doktori (PhD) dissertatsiya ishi himoyasi to‘g‘risida",
        "exam_subjects": [],
        "study_forms": [],
        "languages": []
      },
      {
        "dirid": "",
        "name": "Nurmatov Eliyor Alimovichning pedagogika fanlari bo‘yicha falsafa doktori (PhD) dissertatsiya ishi himoyasi to‘g‘risida",
        "exam_subjects": [],
        "study_forms": [],
        "languages": []
      },
      {
        "dirid": "",
        "name": "Pirov Mustakim Saidovichning texnika fanlari bo’yicha falsafa doktori (PhD) dissertatsiya ishi himoyasi to‘g‘risida",
        "exam_subjects": [],
        "study_forms": [],
        "languages": []
      },
      {
        "dirid": "",
        "name": "Xojabayev Alisher Maxmudovichning texnika fanlari bo‘yicha falsafa doktori (PhD) dissertatsiya ishi himoyasi to‘g‘risida",
        "exam_subjects": [],
        "study_forms": [],
        "languages": []
      }
    ],
    "master_count": 0,
    "doctorate_count": 9,
    "note": "website:https://taqu.uz pages=4"
  },
  "Toshkent davlat sharqshunoslik universiteti": {
    "website": "https://tsuos.uz/",
    "master_directions": [
      {
        "dirid": "70220601",
        "name": "Etnografiya, etnologiya va antropologiya",
        "exam_subjects": [],
        "study_forms": [],
        "languages": []
      },
      {
        "dirid": "70220502",
        "name": "Sharq falsafasi va madaniyati",
        "exam_subjects": [],
        "study_forms": [],
        "languages": []
      },
      {
        "dirid": "70220503",
        "name": "Tasavvuf germenevtikasi",
        "exam_subjects": [],
        "study_forms": [],
        "languages": []
      }
    ],
    "doctorate_directions": [],
    "master_count": 3,
    "doctorate_count": 0,
    "note": "website:https://tsuos.uz/ pages=24"
  },
  "Toshkent davlat tibbiyot universiteti": {
    "website": "https://tma.uz",
    "master_directions": [
      {
        "dirid": "70910209",
        "name": "Nevrologiya-nervnye-bolezni.doc\">Квалификационные требования к специальности магистратуры 70910209-Неврология (нервные болезни)",
        "exam_subjects": [],
        "study_forms": [],
        "languages": []
      },
      {
        "dirid": "70910217",
        "name": "Urologiya-oquv-jadvali.pdf\">70910217-Urologiya o’quv jadvali",
        "exam_subjects": [],
        "study_forms": [],
        "languages": []
      }
    ],
    "doctorate_directions": [],
    "master_count": 2,
    "doctorate_count": 0,
    "note": "website:https://tma.uz pages=19"
  },
  "Toshkent davlat tibbiyot universiteti Termiz filiali": {
    "website": "https://ttatf.uz/",
    "master_directions": [],
    "doctorate_directions": [
      {
        "dirid": "",
        "name": "Doktorantura – TOSHKENT DAVLAT TIBBIYOT UNIVERSITETI TERMIZ FILIALI Skip to content +998-55-452-55-86",
        "exam_subjects": [],
        "study_forms": [],
        "languages": []
      },
      {
        "dirid": "",
        "name": "phd – TOSHKENT DAVLAT TIBBIYOT UNIVERSITETI TERMIZ FILIALI Skip to content +998-55-452-55-86",
        "exam_subjects": [],
        "study_forms": [],
        "languages": []
      }
    ],
    "master_count": 0,
    "doctorate_count": 2,
    "note": "website:https://ttatf.uz/ pages=15"
  },
  "Toshkent davlat yuridik universiteti": {
    "website": "https://tsul.uz",
    "master_directions": [
      {
        "dirid": "70420101",
        "name": "Advokatlik faoliyati mutaxassisligi",
        "exam_subjects": [],
        "study_forms": [],
        "languages": []
      },
      {
        "dirid": "70420129",
        "name": "Atrof-muhit huquqi va barqaror rivojlanish mutaxassisligi",
        "exam_subjects": [],
        "study_forms": [],
        "languages": []
      },
      {
        "dirid": "70420108",
        "name": "Biznes huquqi mutaxassisligi",
        "exam_subjects": [],
        "study_forms": [],
        "languages": []
      },
      {
        "dirid": "70420106",
        "name": "Davlat boshqaruvi huquqi mutaxassisligi",
        "exam_subjects": [],
        "study_forms": [],
        "languages": []
      },
      {
        "dirid": "70420123",
        "name": "Intellektual mulk va axborot texnologiyalari huquqi mutaxassisligi",
        "exam_subjects": [],
        "study_forms": [],
        "languages": []
      },
      {
        "dirid": "70420114",
        "name": "Jinoyat qonunchiligini qо‘llash nazariyasi va amaliyoti mutaxassisligi",
        "exam_subjects": [],
        "study_forms": [],
        "languages": []
      },
      {
        "dirid": "70420131",
        "name": "Kiber huquqi mutaxassisligi",
        "exam_subjects": [],
        "study_forms": [],
        "languages": []
      },
      {
        "dirid": "70420126",
        "name": "Korrupsiyaga qarshi kurashish va komplayens nazorati mutaxassisligi",
        "exam_subjects": [],
        "study_forms": [],
        "languages": []
      },
      {
        "dirid": "70420125",
        "name": "Mediatsiya va nizolarni muqobil hal etish usullari mutaxassisligi",
        "exam_subjects": [],
        "study_forms": [],
        "languages": []
      },
      {
        "dirid": "70420113",
        "name": "Mehnat huquqi mutaxassisligi",
        "exam_subjects": [],
        "study_forms": [],
        "languages": []
      },
      {
        "dirid": "70420127",
        "name": "Ommaviy axborot vositalari huquqi mutaxassisligi",
        "exam_subjects": [],
        "study_forms": [],
        "languages": []
      },
      {
        "dirid": "70420105",
        "name": "Sport huquqi mutaxassisligi",
        "exam_subjects": [],
        "study_forms": [],
        "languages": []
      },
      {
        "dirid": "70420102",
        "name": "Xalqaro arbitraj va nizolarni hal etish mutaxassisligi",
        "exam_subjects": [],
        "study_forms": [],
        "languages": []
      },
      {
        "dirid": "70420130",
        "name": "Xalqaro tijorat huquqi mutaxassisligi",
        "exam_subjects": [],
        "study_forms": [],
        "languages": []
      }
    ],
    "doctorate_directions": [],
    "master_count": 14,
    "doctorate_count": 0,
    "note": "website:https://tsul.uz pages=6"
  }
}
